README.md
oapilib/__init__.py
oapilib/core/__init__.py
oapilib/core/client.py
oapilib/core/config.py
pyproject.toml
oapilib-0.0.1.dist-info/entry_points.txt
oapilib-0.0.1.dist-info/WHEEL
oapilib-0.0.1.dist-info/METADATA
oapilib-0.0.1.dist-info/RECORD
